mr_reg.v
//Multiplier register with enable
module mr_reg(clk, reset, mr_in, product, PRODUCT);

  input clk, reset, mr_in;
  input [31 : 0] product;
  output reg [31 : 0] PRODUCT = 0;

  // Your code begins here
always @(posedge clk) 
	begin 
		if(reset == 1) begin 
			PRODUCT <= 0; 
		end else if(mr_in == 1) begin
		 	PRODUCT <= product; 
		end 
	end 
endmodule

b_reg.v
//B register with enable
module b_reg(clk, reset, b_in, b, B);

  input clk, reset, b_in;
  input [31 : 0] b;
  output reg [31 : 0] B = 0;

  // Your code begins here
always @(posedge clk) 
	begin 
		if(reset == 1) begin 
			B <= 0; 
		end else if(b_in == 1) begin
		 	B <= b; 
		end 
	end 
endmodule

a_reg.v
//Partial Sum Register with enable
module a_reg(clk, reset, a_in, a, A);

  input clk, reset, a_in;
  input [31 : 0] a;
  output reg [31 : 0] A = 0;

  // Your code begins here
always @(posedge clk) 
	begin 
		if(reset == 1) begin 
			A <= 0; 
		end else if(a_in == 1) begin
		 	A <= a; 
		end /*else begin 
			A <= 0; 
		end */
	end 
endmodule

sramb.v
//SRAMB
module sramb(
clk,
write,
wdata,
address,
rdata
);

input clk;
input write;
input [31:0] wdata;
input [3:0] address;
output reg [31:0] rdata; //had to make this a register to use in procedure? 

reg[31:0] mem [0:9];


// your code begins here

initial 
begin
 mem [0] = 32'h00018000;
 mem [1] = 32'h00018000;
 mem [2] = 32'h00050000;
 mem [3] = 32'h00020000;
 mem [4] = 32'h00050000;
 mem [5] = 32'h00030000;
 mem [6] = 32'h00038000;
 mem [7] = 32'h00050000;
 mem [8] = 32'h00040000;
 mem [9] = 32'h00030000;
end


/*initial 
begin
 mem [0] = 32'h00010000;
 mem [1] = 32'h00010000;
 mem [2] = 32'h00010000;
 mem [3] = 32'h00010000;
 mem [4] = 32'h00010000;
 mem [5] = 32'h00010000;
 mem [6] = 32'h00010000;
 mem [7] = 32'h00010000;
 mem [8] = 32'h00010000;
 mem [9] = 32'h00010000;
end
*/

always @(posedge clk)
begin 
	if (write == 1)begin 
	mem[address] <= wdata; 
	//rdata <= z; //check this
	end else if(write == 0)begin 
	rdata <= mem[address]; 
	end /* else begin 
	rdata <= z; //check this	
	end*/
end 
endmodule

srama.v
//SRAMA
module srama(
clk,
write,
wdata,
address,
rdata
);

input clk;
input write;
input [31:0] wdata;
input [3:0] address;
output reg [31:0] rdata; //had to make this a register to use in procedure? 

reg[31:0] mem [0:9];



// your code begins here

initial 
begin
 mem [0] = 32'h00014000;
 mem [1] = 32'h00028000;
 mem [2] = 32'h00028000;
 mem [3] = 32'h00020000;
 mem [4] = 32'h00030000;
 mem [5] = 32'h00020000;
 mem [6] = 32'h00014000;
 mem [7] = 32'h00038000;
 mem [8] = 32'h00048000;
 mem [9] = 32'h00020000;
end



/*initial 
begin
 mem [0] = 32'h00020000;
 mem [1] = 32'h00010000;
 mem [2] = 32'h00010000;
 mem [3] = 32'h00010000;
 mem [4] = 32'h00010000;
 mem [5] = 32'h00010000;
 mem [6] = 32'h00010000;
 mem [7] = 32'h00010000;
 mem [8] = 32'h00010000;
 mem [9] = 32'h00010000;
end
*/
always @(posedge clk)
begin 
	if (write == 1)begin 
	mem[address] <= wdata; 
	//rdata <= z; //check this

	end else if(write == 0)begin 
	rdata <= mem[address]; 
	end /*else begin 
	rdata <= z; //check this	
	end */
end

endmodule

fs_reg.v
//Register with enable
module fs_reg(clk, reset, fs_in, ps, fs);

  input clk, reset, fs_in;
  input [31 : 0] ps;
  output reg [31 : 0] fs;

  // Your code begins here
always @(posedge clk) 
	begin 
		if(reset == 1) begin 
			fs <= 0; 
		end else if(fs_in == 1) begin
		 	fs <= ps; 
		end 
	end 
endmodule

ps_reg.v
//Partial Sum Register with enable
module ps_reg(clk, reset, ps_in, sum, ps);

  input clk, reset, ps_in;
  input [31 : 0] sum;
  output reg [31 : 0] ps = 0;

  // Your code begins here
always @(posedge clk) 
	begin 
		if(reset == 1) begin 
			ps <= 0; 
		end else if (ps_in == 1) begin
		      ps <= sum; 
		end
	end 
endmodule

adder.v
//ADD WITH ENABLE
module adder(clk, PRODUCT, ps, sum, add_enable);
 //does this need a reset?
  //input [31 : 0] product; //output from multiplier
  input clk;
  input [31:0] PRODUCT; 
  input [31:0] ps; //PARTIAL SUM REGISTER
  input add_enable; //for testing purposes
 
  output reg [31:0] sum;

  // Your code begins here

always @ (posedge clk)
begin
	if (add_enable == 1)begin  
	sum <= PRODUCT + ps; 
	end 
	//end else begin
		//SUM <= 0; 
	//end
end

endmodule

mult.v
//MULTIPLY
//need to check states to add a done signal after 32 iterations
module mult(clk, reset, A, B, product, done, multiply_enable);

  input clk;
  input reset;
  input multiply_enable; //begins multiplication 

  input [31 : 0] B;
  input [31 : 0] A;
  output reg [31:0] product = 0; 
  output reg done = 0; //Done signal to control
  //output reg [31 : 0] product = 0;


  // Your code begins here

//DEFINING STATES OF FSM
parameter[2:0] SET = 3'b000;
parameter[2:0] MULTIPLY = 3'b001;
parameter[2:0] DONE = 3'b010;
parameter[2:0] IDLE = 3'b011; 

reg[63:0] prod =0;

reg[2:0]STATE = SET;
reg[2:0]NEXT_STATE = SET;

//process to implement the state register
always @ (posedge clk)
begin
	if(reset == 1'b1)begin
	STATE <= SET;
	end else if(reset == 1'b0)begin
	STATE <= NEXT_STATE;
	end
end

//process to determine next state 
always @ (STATE or multiply_enable)
begin
	case(STATE)
		SET: if(multiply_enable == 1)begin
			 		NEXT_STATE <= MULTIPLY; 
			 	end else if(multiply_enable == 0)begin 
			 		NEXT_STATE <= SET;
				end
		MULTIPLY: NEXT_STATE <= DONE;
		
		DONE: NEXT_STATE <= IDLE;  

		IDLE: if(multiply_enable == 1)begin
			 		NEXT_STATE <= MULTIPLY; 
			 	end else if(multiply_enable == 0)begin 
			 		NEXT_STATE <= IDLE;
				end

		default : NEXT_STATE <= SET;
	endcase
end

//statement to define the output values
always@(STATE or A or B) begin
	if(STATE == SET) begin 
		done <= 0; 
		product <= 0; 

	end else if(STATE == MULTIPLY)begin
		prod <= (A*B); 
		done <= 0;

	end else if(STATE == DONE)begin
		product <= prod[48:16];
		done <= 1; 
	end else if (STATE == IDLE)begin 
		done <= 0;
	end
end
endmodule

control.v
module control(
	clk, // clk
	reset, // Active high, syn reset
	done, // Done signal from multiplier
	address, //Address to memory
	ps_in, //Partial sum register enable
	fs_in,//Final sum register enable
	a_in, 
	b_in, 
	mr_in, 
	fs_out, //Final sum register output tri-state enable 
	write, //Memory write enable
	multiply_enable,
	add_enable,
	STATE 
);

// Input Declaration
input  clk,reset,done;

// Ouput Declaration 
output reg  ps_in, fs_in, fs_out, a_in, b_in, mr_in, write; 
output reg multiply_enable, add_enable; 
output reg[3:0] address = 4'b0000; 
	
reg[5:0] count = 6'b0;  

//---Defining States---
parameter[2:0] S0 = 3'b000;
parameter[2:0] S1 = 3'b001; 
/*parameter[2:0] S2 = 3'b010; 
parameter[2:0] S3 = 3'b011;
parameter[2:0] S4 = 3'b100;
*/

output reg[2:0]STATE = S0;
reg[2:0]NEXT_STATE = S0;

//---process to implement the state register---

initial begin 
	write = 0; //reading from SRAM only
	add_enable = 1; 
end 

always @ (posedge clk)
begin
	if(reset==1'b1)begin
	STATE = S0;
	//count = 0; 
	address = 4'b0000; 
	end else if(reset==1'b0)begin
	STATE = NEXT_STATE;
	end
end

//---process to determine next state---


always @ (STATE or done)
begin
	case(STATE)
		S0: NEXT_STATE = S1;

		S1: if (done == 1) begin 
			NEXT_STATE = S0;
		end else if (done == 0)begin 
			NEXT_STATE = S1; 
		end

		default: NEXT_STATE = S0;
	endcase
end

//---statement to define the output values---

always@(STATE) begin
	case (STATE)
	
		S0: begin
		ps_in <= 1; 
		fs_in <= 0; 
		//fs_out<= 0;
		a_in <= 1; 
		b_in <= 1; 
		mr_in <= 1;   
 		multiply_enable <= 0;  
		//add_enable <= 0; 
		end
			
		S1: begin
		address <= address + 1; 
		ps_in <= 0; 
		fs_in <= 0; 
		//fs_out<= 0;
		a_in <= 0; 
		b_in <= 0; 
		mr_in <= 0;   
 		multiply_enable <= 1;  
		//add_enable <= 1; 
		end

		default:begin
		ps_in <= 0; 
		fs_in <= 0; 
		//fs_out<= 0;
		a_in <= 0; 
		b_in <= 0; 
		mr_in <= 0;   
 		multiply_enable <= 0;  
		//add_enable <= 0; 
		end
	endcase
end

endmodule

top.v
//TOP
module top(
clk,
reset
);

//---Inputs---
input clk;
input reset;

wire done;   //Multiplier done signal 
wire ps_in;  //partial sum register enable 
wire fs_in;  //final sum register enable 
wire fs_out; //final sum register output enable
wire a_in;   //a_reg enable 
wire b_in;   //b_reg enable
wire mr_in; 
wire write;  //write signal for SRAM (write = 0 implies read)

wire [31:0] A ; //output of a_reg 
wire [31:0] B ; //output of b_reg
wire [31:0] a ; //output of SRAMA
wire [31:0] b ; //output of SRAMB

wire [31:0] product;
wire [31:0] PRODUCT;
wire [31:0] ps; //partial sum
wire [31:0] sum; 
wire [31:0] fs; //final sum
wire [3:0] address;
wire [31:0] wdata; //data to SRAM


wire add_enable; 
wire multiply_enable; //Multiply enable  
//input ps_in; //Partial Sum register enable

control CONTROL(.clk(clk), 
	.reset(reset), 
	.done(done),
	.ps_in(ps_in), 
	.fs_in(fs_in), 
	.a_in(a_in), 
	.b_in(b_in), 
	.mr_in(mr_in),
	.address(address),
	.write(write),
	.multiply_enable(multiply_enable),
	.add_enable(add_enable),
	.fs_out(fs_out));

mult MULT(.clk(clk), 
	.product(product),
	.reset(reset),
	.done(done), 
	.multiply_enable(multiply_enable),
	.A(A),  //multiplier from srama
	.B(B));  //multiplier from sramb
	//.PRODUCT(PRODUCT)); //truncated floating point product 

adder ADDER(.clk(clk), 
	.PRODUCT(PRODUCT), 
	.ps(ps), 
 	.add_enable(add_enable), 
	.sum(sum)); 

ps_reg PS_REG(.clk(clk), 
	.reset(reset), 
	.ps_in(ps_in), 
	.sum(sum), 
	.ps(ps));

fs_reg FS_REG(.clk(clk), 
	.reset(reset), 
	.fs_in(fs_in),
	.ps(ps), 
	.fs(fs)); 
	
srama SRAMA(.clk(clk),
	.wdata(wdata), 
	.write(write),  
	.address(address), 
	.rdata(a)); 

sramb SRAMB(.clk(clk),
	.wdata(wdata),
	.write(write),  
	.address(address), 
	.rdata(b));  

a_reg A_REG(.clk(clk), 
	.reset(reset), 
	.a_in(a_in), 
	.a(a), 
	.A(A));

b_reg B_REG(.clk(clk), 
	.reset(reset), 
	.b_in(b_in), 
	.b(b), 
	.B(B));

mr_reg MR_REG(.clk(clk), 
	.reset(reset), 
	.mr_in(mr_in), 
	.product(product), 
	.PRODUCT(PRODUCT));

endmodule

top_tb.v

`timescale 1ns / 1ps

module top_tb();
	reg  clk;
	reg  reset;
//	reg [31:0] A = 32'h0000ffff; 
	//reg [31:0] B = 32'h00010000; 
	

    top DUT(
        .clk(clk),
        .reset(reset)
	//.A(A), 
	//.B(B)
        );

    initial
    begin
        $dumpfile("top.vcd");
        $dumpvars(0, top_tb);


		clk = 0;
		reset = 1;

		#20
		reset = 0;

	
		#10000
		$finish;

        $finish;
    end

    always 
        #10 clk = !clk;

endmodule

top.vcd
$date
	Sat Nov 18 21:04:01 2017
$end

$version
	Synopsys VCS version J-2014.12-SP1-1_Full64
$end

$timescale
	1ps
$end

$comment Csum: 1 e4f468586a9b6512 $end


$scope module top_tb $end
$var reg 1 ! clk $end
$var reg 1 " reset $end

$scope module DUT $end
$var wire 1 ! clk $end
$var wire 1 " reset $end
$var wire 1 # done $end
$var wire 1 $ ps_in $end
$var wire 1 % fs_in $end
$var wire 1 & fs_out $end
$var wire 1 ' a_in $end
$var wire 1 ( b_in $end
$var wire 1 ) mr_in $end
$var wire 1 * write $end
$var wire 32 + A [31:0] $end
$var wire 32 , B [31:0] $end
$var wire 32 - a [31:0] $end
$var wire 32 . b [31:0] $end
$var wire 32 / product [31:0] $end
$var wire 32 0 PRODUCT [31:0] $end
$var wire 32 1 ps [31:0] $end
$var wire 32 2 sum [31:0] $end
$var wire 32 3 fs [31:0] $end
$var wire 4 4 address [3:0] $end
$var wire 32 5 wdata [31:0] $end
$var wire 1 6 add_enable $end
$var wire 1 7 multiply_enable $end

$scope module CONTROL $end
$var wire 1 ! clk $end
$var wire 1 " reset $end
$var wire 1 # done $end
$var reg 1 8 ps_in $end
$var reg 1 9 fs_in $end
$var reg 1 & fs_out $end
$var reg 1 : a_in $end
$var reg 1 ; b_in $end
$var reg 1 < mr_in $end
$var reg 1 = write $end
$var reg 1 > multiply_enable $end
$var reg 1 ? add_enable $end
$var reg 4 @ address [3:0] $end
$var reg 6 A count [5:0] $end
$var reg 3 B STATE [2:0] $end
$var reg 3 C NEXT_STATE [2:0] $end
$upscope $end


$scope module MULT $end
$var wire 1 ! clk $end
$var wire 1 " reset $end
$var wire 1 7 multiply_enable $end
$var wire 32 , B [31:0] $end
$var wire 32 + A [31:0] $end
$var reg 32 D product [31:0] $end
$var reg 1 E done $end
$var reg 64 F prod [63:0] $end
$var reg 3 G STATE [2:0] $end
$var reg 3 H NEXT_STATE [2:0] $end
$upscope $end


$scope module ADDER $end
$var wire 1 ! clk $end
$var wire 32 0 PRODUCT [31:0] $end
$var wire 32 1 ps [31:0] $end
$var wire 1 6 add_enable $end
$var reg 32 I sum [31:0] $end
$upscope $end


$scope module PS_REG $end
$var wire 1 ! clk $end
$var wire 1 " reset $end
$var wire 1 $ ps_in $end
$var wire 32 2 sum [31:0] $end
$var reg 32 J ps [31:0] $end
$upscope $end


$scope module FS_REG $end
$var wire 1 ! clk $end
$var wire 1 " reset $end
$var wire 1 % fs_in $end
$var wire 32 1 ps [31:0] $end
$var reg 32 3 fs [31:0] $end
$upscope $end


$scope module SRAMA $end
$var wire 1 ! clk $end
$var wire 1 * write $end
$var wire 32 5 wdata [31:0] $end
$var wire 4 4 address [3:0] $end
$var reg 32 K rdata [31:0] $end
$upscope $end


$scope module SRAMB $end
$var wire 1 ! clk $end
$var wire 1 * write $end
$var wire 32 5 wdata [31:0] $end
$var wire 4 4 address [3:0] $end
$var reg 32 L rdata [31:0] $end
$upscope $end


$scope module A_REG $end
$var wire 1 ! clk $end
$var wire 1 " reset $end
$var wire 1 ' a_in $end
$var wire 32 - a [31:0] $end
$var reg 32 M A [31:0] $end
$upscope $end


$scope module B_REG $end
$var wire 1 ! clk $end
$var wire 1 " reset $end
$var wire 1 ( b_in $end
$var wire 32 . b [31:0] $end
$var reg 32 N B [31:0] $end
$upscope $end


$scope module MR_REG $end
$var wire 1 ! clk $end
$var wire 1 " reset $end
$var wire 1 ) mr_in $end
$var wire 32 / product [31:0] $end
$var reg 32 O PRODUCT [31:0] $end
$upscope $end

$upscope $end

$upscope $end

$enddefinitions $end

#0
$dumpvars
1:
1?
1;
09
x&
1<
0>
18
0=
0E
1'
16
1(
0!
0#
0%
1)
07
1$
1"
0*
b00000000000000000000000000000000 +
bxxxxxxxxxxxxxxxxxxxxxxxxxxxxxxxx I
b00000000000000000000000000000000 M
b00000000000000000000000000000000 ,
b00000000000000000000000000000000 N
b0000 @
b00000000000000000000000000000000 O
b000 H
b000 G
b00000000000000000000000000000000 D
b001 C
b00000000000000000000000000000000 0
b00000000000000000000000000000000 J
bxxxxxxxxxxxxxxxxxxxxxxxxxxxxxxxx L
b000 B
bxxxxxxxxxxxxxxxxxxxxxxxxxxxxxxxx -
b0000 4
bxxxxxxxxxxxxxxxxxxxxxxxxxxxxxxxx .
b000000 A
bxxxxxxxxxxxxxxxxxxxxxxxxxxxxxxxx 3
b0000000000000000000000000000000000000000000000000000000000000000 F
b00000000000000000000000000000000 /
b00000000000000000000000000000000 1
bxxxxxxxxxxxxxxxxxxxxxxxxxxxxxxxx K
bxxxxxxxxxxxxxxxxxxxxxxxxxxxxxxxx 2
bzzzzzzzzzzzzzzzzzzzzzzzzzzzzzzzz 5
$end
#10000
1!
b00000000000000000000000000000000 I
b00000000000000000000000000000000 2
b00000000000000000000000000000000 3
b00000000000000010100000000000000 K
b00000000000000010100000000000000 -
b00000000000000011000000000000000 L
b00000000000000011000000000000000 .
#20000
0"
0!
#30000
1!
b001 B
b00000000000000010100000000000000 M
b00000000000000010100000000000000 +
b00000000000000011000000000000000 N
b00000000000000011000000000000000 ,
b0001 @
b0001 4
08
0$
0:
0'
0;
0(
0<
0)
1>
17
b001 H
#40000
0!
#50000
1!
b001 G
b00000000000000101000000000000000 K
b00000000000000101000000000000000 -
b010 H
b0000000000000000000000000000000111100000000000000000000000000000 F
#60000
0!
#70000
1!
b010 G
b011 H
b00000000000000011110000000000000 D
b00000000000000011110000000000000 /
1E
1#
b000 C
#80000
0!
#90000
1!
b000 B
b001 C
b011 G
18
1$
1:
1'
1;
1(
1<
1)
0>
07
0E
0#
#100000
0!
#110000
1!
b001 B
b00000000000000101000000000000000 M
b00000000000000101000000000000000 +
b00000000000000011110000000000000 O
b00000000000000011110000000000000 0
b0010 @
b0010 4
08
0$
0:
0'
0;
0(
0<
0)
1>
17
b001 H
#120000
0!
#130000
1!
b001 G
b00000000000000011110000000000000 I
b00000000000000011110000000000000 2
b00000000000001010000000000000000 L
b00000000000001010000000000000000 .
b010 H
b0000000000000000000000000000001111000000000000000000000000000000 F
#140000
0!
#150000
1!
b010 G
b011 H
b00000000000000111100000000000000 D
b00000000000000111100000000000000 /
1E
1#
b000 C
#160000
0!
#170000
1!
b000 B
b001 C
b011 G
18
1$
1:
1'
1;
1(
1<
1)
0>
07
0E
0#
#180000
0!
#190000
1!
b001 B
b00000000000000011110000000000000 J
b00000000000000011110000000000000 1
b00000000000001010000000000000000 N
b00000000000001010000000000000000 ,
b00000000000000111100000000000000 O
b00000000000000111100000000000000 0
b0011 @
b0011 4
08
0$
0:
0'
0;
0(
0<
0)
1>
17
b001 H
#200000
0!
#210000
1!
b001 G
b00000000000001011010000000000000 I
b00000000000001011010000000000000 2
b00000000000000100000000000000000 K
b00000000000000100000000000000000 -
b00000000000000100000000000000000 L
b00000000000000100000000000000000 .
b010 H
b0000000000000000000000000000110010000000000000000000000000000000 F
#220000
0!
#230000
1!
b010 G
b011 H
b00000000000011001000000000000000 D
b00000000000011001000000000000000 /
1E
1#
b000 C
#240000
0!
#250000
1!
b000 B
b001 C
b011 G
18
1$
1:
1'
1;
1(
1<
1)
0>
07
0E
0#
#260000
0!
#270000
1!
b001 B
b00000000000001011010000000000000 J
b00000000000001011010000000000000 1
b00000000000000100000000000000000 M
b00000000000000100000000000000000 +
b00000000000000100000000000000000 N
b00000000000000100000000000000000 ,
b00000000000011001000000000000000 O
b00000000000011001000000000000000 0
b0100 @
b0100 4
08
0$
0:
0'
0;
0(
0<
0)
1>
17
b001 H
#280000
0!
#290000
1!
b001 G
b00000000000100100010000000000000 I
b00000000000100100010000000000000 2
b00000000000000110000000000000000 K
b00000000000000110000000000000000 -
b00000000000001010000000000000000 L
b00000000000001010000000000000000 .
b010 H
b0000000000000000000000000000010000000000000000000000000000000000 F
#300000
0!
#310000
1!
b010 G
b011 H
b00000000000001000000000000000000 D
b00000000000001000000000000000000 /
1E
1#
b000 C
#320000
0!
#330000
1!
b000 B
b001 C
b011 G
18
1$
1:
1'
1;
1(
1<
1)
0>
07
0E
0#
#340000
0!
#350000
1!
b001 B
b00000000000100100010000000000000 J
b00000000000100100010000000000000 1
b00000000000000110000000000000000 M
b00000000000000110000000000000000 +
b00000000000001010000000000000000 N
b00000000000001010000000000000000 ,
b00000000000001000000000000000000 O
b00000000000001000000000000000000 0
b0101 @
b0101 4
08
0$
0:
0'
0;
0(
0<
0)
1>
17
b001 H
#360000
0!
#370000
1!
b001 G
b00000000000101100010000000000000 I
b00000000000101100010000000000000 2
b00000000000000100000000000000000 K
b00000000000000100000000000000000 -
b00000000000000110000000000000000 L
b00000000000000110000000000000000 .
b010 H
b0000000000000000000000000000111100000000000000000000000000000000 F
#380000
0!
#390000
1!
b010 G
b011 H
b00000000000011110000000000000000 D
b00000000000011110000000000000000 /
1E
1#
b000 C
#400000
0!
#410000
1!
b000 B
b001 C
b011 G
18
1$
1:
1'
1;
1(
1<
1)
0>
07
0E
0#
#420000
0!
#430000
1!
b001 B
b00000000000101100010000000000000 J
b00000000000101100010000000000000 1
b00000000000000100000000000000000 M
b00000000000000100000000000000000 +
b00000000000000110000000000000000 N
b00000000000000110000000000000000 ,
b00000000000011110000000000000000 O
b00000000000011110000000000000000 0
b0110 @
b0110 4
08
0$
0:
0'
0;
0(
0<
0)
1>
17
b001 H
#440000
0!
#450000
1!
b001 G
b00000000001001010010000000000000 I
b00000000001001010010000000000000 2
b00000000000000010100000000000000 K
b00000000000000010100000000000000 -
b00000000000000111000000000000000 L
b00000000000000111000000000000000 .
b010 H
b0000000000000000000000000000011000000000000000000000000000000000 F
#460000
0!
#470000
1!
b010 G
b011 H
b00000000000001100000000000000000 D
b00000000000001100000000000000000 /
1E
1#
b000 C
#480000
0!
#490000
1!
b000 B
b001 C
b011 G
18
1$
1:
1'
1;
1(
1<
1)
0>
07
0E
0#
#500000
0!
#510000
1!
b001 B
b00000000001001010010000000000000 J
b00000000001001010010000000000000 1
b00000000000000010100000000000000 M
b00000000000000010100000000000000 +
b00000000000000111000000000000000 N
b00000000000000111000000000000000 ,
b00000000000001100000000000000000 O
b00000000000001100000000000000000 0
b0111 @
b0111 4
08
0$
0:
0'
0;
0(
0<
0)
1>
17
b001 H
#520000
0!
#530000
1!
b001 G
b00000000001010110010000000000000 I
b00000000001010110010000000000000 2
b00000000000000111000000000000000 K
b00000000000000111000000000000000 -
b00000000000001010000000000000000 L
b00000000000001010000000000000000 .
b010 H
b0000000000000000000000000000010001100000000000000000000000000000 F
#540000
0!
#550000
1!
b010 G
b011 H
b00000000000001000110000000000000 D
b00000000000001000110000000000000 /
1E
1#
b000 C
#560000
0!
#570000
1!
b000 B
b001 C
b011 G
18
1$
1:
1'
1;
1(
1<
1)
0>
07
0E
0#
#580000
0!
#590000
1!
b001 B
b00000000001010110010000000000000 J
b00000000001010110010000000000000 1
b00000000000000111000000000000000 M
b00000000000000111000000000000000 +
b00000000000001010000000000000000 N
b00000000000001010000000000000000 ,
b00000000000001000110000000000000 O
b00000000000001000110000000000000 0
b1000 @
b1000 4
08
0$
0:
0'
0;
0(
0<
0)
1>
17
b001 H
#600000
0!
#610000
1!
b001 G
b00000000001011111000000000000000 I
b00000000001011111000000000000000 2
b00000000000001001000000000000000 K
b00000000000001001000000000000000 -
b00000000000001000000000000000000 L
b00000000000001000000000000000000 .
b010 H
b0000000000000000000000000001000110000000000000000000000000000000 F
#620000
0!
#630000
1!
b010 G
b011 H
b00000000000100011000000000000000 D
b00000000000100011000000000000000 /
1E
1#
b000 C
#640000
0!
#650000
1!
b000 B
b001 C
b011 G
18
1$
1:
1'
1;
1(
1<
1)
0>
07
0E
0#
#660000
0!
#670000
1!
b001 B
b00000000001011111000000000000000 J
b00000000001011111000000000000000 1
b00000000000001001000000000000000 M
b00000000000001001000000000000000 +
b00000000000001000000000000000000 N
b00000000000001000000000000000000 ,
b00000000000100011000000000000000 O
b00000000000100011000000000000000 0
b1001 @
b1001 4
08
0$
0:
0'
0;
0(
0<
0)
1>
17
b001 H
#680000
0!
#690000
1!
b001 G
b00000000010000010000000000000000 I
b00000000010000010000000000000000 2
b00000000000000100000000000000000 K
b00000000000000100000000000000000 -
b00000000000000110000000000000000 L
b00000000000000110000000000000000 .
b010 H
b0000000000000000000000000001001000000000000000000000000000000000 F
#700000
0!
#710000
1!
b010 G
b011 H
b00000000000100100000000000000000 D
b00000000000100100000000000000000 /
1E
1#
b000 C
#720000
0!
#730000
1!
b000 B
b001 C
b011 G
18
1$
1:
1'
1;
1(
1<
1)
0>
07
0E
0#
#740000
0!
#750000
1!
b001 B
b00000000010000010000000000000000 J
b00000000010000010000000000000000 1
b00000000000000100000000000000000 M
b00000000000000100000000000000000 +
b00000000000000110000000000000000 N
b00000000000000110000000000000000 ,
b00000000000100100000000000000000 O
b00000000000100100000000000000000 0
b1010 @
b1010 4
08
0$
0:
0'
0;
0(
0<
0)
1>
17
b001 H
#760000
0!
#770000
1!
b001 G
b00000000010100110000000000000000 I
b00000000010100110000000000000000 2
bxxxxxxxxxxxxxxxxxxxxxxxxxxxxxxxx K
bxxxxxxxxxxxxxxxxxxxxxxxxxxxxxxxx -
bxxxxxxxxxxxxxxxxxxxxxxxxxxxxxxxx L
bxxxxxxxxxxxxxxxxxxxxxxxxxxxxxxxx .
b010 H
b0000000000000000000000000000011000000000000000000000000000000000 F
#780000
0!
#790000
1!
b010 G
b011 H
b00000000000001100000000000000000 D
b00000000000001100000000000000000 /
1E
1#
b000 C
#800000
0!
#810000
1!
b000 B
b001 C
b011 G
18
1$
1:
1'
1;
1(
1<
1)
0>
07
0E
0#
#820000
0!
#830000
1!
b001 B
b00000000010100110000000000000000 J
b00000000010100110000000000000000 1
bxxxxxxxxxxxxxxxxxxxxxxxxxxxxxxxx M
bxxxxxxxxxxxxxxxxxxxxxxxxxxxxxxxx +
bxxxxxxxxxxxxxxxxxxxxxxxxxxxxxxxx N
bxxxxxxxxxxxxxxxxxxxxxxxxxxxxxxxx ,
b00000000000001100000000000000000 O
b00000000000001100000000000000000 0
b1011 @
b1011 4
08
0$
0:
0'
0;
0(
0<
0)
1>
17
b001 H
#840000
0!
#850000
1!
b001 G
b00000000010110010000000000000000 I
b00000000010110010000000000000000 2
b010 H
bxxxxxxxxxxxxxxxxxxxxxxxxxxxxxxxxxxxxxxxxxxxxxxxxxxxxxxxxxxxxxxxx F
#860000
0!
#870000
1!
b010 G
b011 H
bxxxxxxxxxxxxxxxxxxxxxxxxxxxxxxxx D
bxxxxxxxxxxxxxxxxxxxxxxxxxxxxxxxx /
1E
1#
b000 C
#880000
0!
#890000
1!
b000 B
b001 C
b011 G
18
1$
1:
1'
1;
1(
1<
1)
0>
07
0E
0#
#900000
0!
#910000
1!
b001 B
b00000000010110010000000000000000 J
b00000000010110010000000000000000 1
bxxxxxxxxxxxxxxxxxxxxxxxxxxxxxxxx O
bxxxxxxxxxxxxxxxxxxxxxxxxxxxxxxxx 0
b1100 @
b1100 4
08
0$
0:
0'
0;
0(
0<
0)
1>
17
b001 H
#920000
0!
#930000
1!
b001 G
bxxxxxxxxxxxxxxxxxxxxxxxxxxxxxxxx I
bxxxxxxxxxxxxxxxxxxxxxxxxxxxxxxxx 2
b010 H
#940000
0!
#950000
1!
b010 G
b011 H
1E
1#
b000 C
#960000
0!
#970000
1!
b000 B
b001 C
b011 G
18
1$
1:
1'
1;
1(
1<
1)
0>
07
0E
0#
#980000
0!
#990000
1!
b001 B
bxxxxxxxxxxxxxxxxxxxxxxxxxxxxxxxx J
bxxxxxxxxxxxxxxxxxxxxxxxxxxxxxxxx 1
b1101 @
b1101 4
08
0$
0:
0'
0;
0(
0<
0)
1>
17
b001 H
#1000000
0!
#1010000
1!
b001 G
b010 H
#1020000
0!
#1030000
1!
b010 G
b011 H
1E
1#
b000 C
#1040000
0!
#1050000
1!
b000 B
b001 C
b011 G
18
1$
1:
1'
1;
1(
1<
1)
0>
07
0E
0#
#1060000
0!
#1070000
1!
b001 B
b1110 @
b1110 4
08
0$
0:
0'
0;
0(
0<
0)
1>
17
b001 H
#1080000
0!
#1090000
1!
b001 G
b010 H
#1100000
0!
#1110000
1!
b010 G
b011 H
1E
1#
b000 C
#1120000
0!
#1130000
1!
b000 B
b001 C
b011 G
18
1$
1:
1'
1;
1(
1<
1)
0>
07
0E
0#
#1140000
0!
#1150000
1!
b001 B
b1111 @
b1111 4
08
0$
0:
0'
0;
0(
0<
0)
1>
17
b001 H
#1160000
0!
#1170000
1!
b001 G
b010 H
#1180000
0!
#1190000
1!
b010 G
b011 H
1E
1#
b000 C
#1200000
0!
#1210000
1!
b000 B
b001 C
b011 G
18
1$
1:
1'
1;
1(
1<
1)
0>
07
0E
0#
#1220000
0!
#1230000
1!
b001 B
b0000 @
b0000 4
08
0$
0:
0'
0;
0(
0<
0)
1>
17
b001 H
#1240000
0!
#1250000
1!
b001 G
b00000000000000010100000000000000 K
b00000000000000010100000000000000 -
b00000000000000011000000000000000 L
b00000000000000011000000000000000 .
b010 H
#1260000
0!
#1270000
1!
b010 G
b011 H
1E
1#
b000 C
#1280000
0!
#1290000
1!
b000 B
b001 C
b011 G
18
1$
1:
1'
1;
1(
1<
1)
0>
07
0E
0#
#1300000
0!
#1310000
1!
b001 B
b00000000000000010100000000000000 M
b00000000000000010100000000000000 +
b00000000000000011000000000000000 N
b00000000000000011000000000000000 ,
b0001 @
b0001 4
08
0$
0:
0'
0;
0(
0<
0)
1>
17
b001 H
#1320000
0!
#1330000
1!
b001 G
b00000000000000101000000000000000 K
b00000000000000101000000000000000 -
b010 H
b0000000000000000000000000000000111100000000000000000000000000000 F
#1340000
0!
#1350000
1!
b010 G
b011 H
b00000000000000011110000000000000 D
b00000000000000011110000000000000 /
1E
1#
b000 C
#1360000
0!
#1370000
1!
b000 B
b001 C
b011 G
18
1$
1:
1'
1;
1(
1<
1)
0>
07
0E
0#
#1380000
0!
#1390000
1!
b001 B
b00000000000000101000000000000000 M
b00000000000000101000000000000000 +
b00000000000000011110000000000000 O
b00000000000000011110000000000000 0
b0010 @
b0010 4
08
0$
0:
0'
0;
0(
0<
0)
1>
17
b001 H
#1400000
0!
#1410000
1!
b001 G
b00000000000001010000000000000000 L
b00000000000001010000000000000000 .
b010 H
b0000000000000000000000000000001111000000000000000000000000000000 F
#1420000
0!
#1430000
1!
b010 G
b011 H
b00000000000000111100000000000000 D
b00000000000000111100000000000000 /
1E
1#
b000 C
#1440000
0!
#1450000
1!
b000 B
b001 C
b011 G
18
1$
1:
1'
1;
1(
1<
1)
0>
07
0E
0#
#1460000
0!
